adhoc_pdb/__init__.py
adhoc_pdb/adhoc_pdb.py
adhoc_pdb/cli.py
adhoc_pdb-0.1.2.dist-info/entry_points.txt
adhoc_pdb-0.1.2.dist-info/LICENSE
adhoc_pdb-0.1.2.dist-info/WHEEL
adhoc_pdb-0.1.2.dist-info/METADATA
adhoc_pdb-0.1.2.dist-info/RECORD
